palindrome_words_lib/__init__.py
palindrome_words_lib/__main__.py
palindrome_words_lib/core.py
palindromewordslib-0.1.0.dist-info/licenses/LICENSE
palindromewordslib-0.1.0.dist-info/METADATA
palindromewordslib-0.1.0.dist-info/WHEEL
palindromewordslib-0.1.0.dist-info/entry_points.txt
palindromewordslib-0.1.0.dist-info/top_level.txt
palindromewordslib-0.1.0.dist-info/RECORD
