Metadata-Version: 2.4
Name: PalindromeWordsLib
Version: 0.1.0
Summary: Extract palindrome words from text
Author: Elaf Jamal Omar
Author-email: Elaf Jamal Omar <o25635635@gmail.com>
License: MIT License
Requires-Python: >=3.7
License-File: LICENSE
Dynamic: author
Dynamic: license-file
Dynamic: requires-python
